x22220445_custom_apparel_calc/__init__.py
x22220445_custom_apparel_calc/custom_apparel_library.py
x22220445_custom_apparel_calc/pricing_constants.py
x22220445_custom_apparel_calc-0.0.2.dist-info/METADATA
x22220445_custom_apparel_calc-0.0.2.dist-info/WHEEL
x22220445_custom_apparel_calc-0.0.2.dist-info/licenses/LICENSE
x22220445_custom_apparel_calc-0.0.2.dist-info/RECORD
