Metadata-Version: 2.1
Name: x22220445_custom_apparel_calc
Version: 0.0.2
Summary: The Custom Apparel Library is a Python library for representing custom apparel with pricing.
Author-email: Balavignesh Kunkulagunta Sanghameswar <x22220445@student.ncirl.ie>
License-File: LICENSE
Classifier: License :: OSI Approved :: MIT License
Classifier: Operating System :: OS Independent
Classifier: Programming Language :: Python :: 3
Requires-Python: >=3.7
